{
  "project_info": {
    "project_number": "46359945356",
    "project_id": "citygates-82da3",
    "storage_bucket": "citygates-82da3.appspot.com"
  },
  "client": [
    {
      "client_info": {
        "mobilesdk_app_id": "1:46359945356:android:ab299ec66609bd0ceb9ba9",
        "android_client_info": {
          "package_name": "com.example.task_management"
        }
      },
      "oauth_client": [],
      "api_key": [
        {
          "current_key": "AIzaSyA20HvcVriGivnsNE7OpJqBFN7Zf6MdNB0"
        }
      ],
      "services": {
        "appinvite_service": {
          "other_platform_oauth_client": []
        }
      }
    }
  ],
  "configuration_version": "1"
}